rsconnect_jupyter/__init__.py
rsconnect_jupyter/managers.py
rsconnect_jupyter/version.py
rsconnect_jupyter/static/.eslintrc.yml
rsconnect_jupyter/static/connect.js
rsconnect_jupyter/static/index.js
rsconnect_jupyter/static/main.css
rsconnect_jupyter/static/rsconnect.js
rsconnect_jupyter/static/version.json
rsconnect_jupyter/static/images/publishDocVoila.png
rsconnect_jupyter/static/images/publishDocVoila_2x.png
rsconnect_jupyter/static/images/publishDocWithSource.png
rsconnect_jupyter/static/images/publishDocWithSource_2x.png
rsconnect_jupyter/static/images/publishDocWithoutSource.png
rsconnect_jupyter/static/images/publishDocWithoutSource_2x.png
rsconnect_jupyter-1.8.1.dist-info/LICENSE.md
rsconnect_jupyter-1.8.1.dist-info/METADATA
rsconnect_jupyter-1.8.1.dist-info/WHEEL
rsconnect_jupyter-1.8.1.dist-info/top_level.txt
rsconnect_jupyter-1.8.1.dist-info/RECORD
