Metadata-Version: 2.1
Name: rsconnect-jupyter
Version: 1.8.1
Summary: Jupyter Notebook integration with Posit Connect
Home-page: http://github.com/rstudio/rsconnect-jupyter
Author: Jonathan Curran
Author-email: jonathan.curran@posit.co
License: GPL-2.0
Project-URL: Documentation, https://docs.posit.co/rsconnect-jupyter
Platform: UNKNOWN
Requires-Python: >=3.8
Requires-Dist: rsconnect-python>=1.15.0
Requires-Dist: notebook<7.0.0,>=6.1.5
Requires-Dist: nbformat
Requires-Dist: nbconvert>=5.6.1
Requires-Dist: six
Requires-Dist: ipython
Provides-Extra: test
Requires-Dist: black; extra == "test"
Requires-Dist: pytest; extra == "test"
